xboxgamertag.py
xboxgamertag-1.0.1.dist-info/METADATA
xboxgamertag-1.0.1.dist-info/WHEEL
xboxgamertag-1.0.1.dist-info/top_level.txt
xboxgamertag-1.0.1.dist-info/RECORD
