Metadata-Version: 2.1
Name: xboxgamertag
Version: 1.0.1
Summary: Python module to get data from www.xboxgamertag.com
Home-page: https://github.com/WoolDoughnut310/xboxgamertag
Author: J. Nma
Author-email: wooldoughnutspi@outlook.com
License: UNKNOWN
Keywords: xbox-gamertag python3 data
Platform: UNKNOWN
Classifier: Development Status :: 5 - Production/Stable
Classifier: Intended Audience :: Developers
Classifier: License :: OSI Approved :: MIT License
Classifier: Topic :: Software Development :: Libraries
Classifier: Programming Language :: Python :: 3
Requires-Python: >=3
Requires-Dist: requests
Requires-Dist: lxml
